jasim_chatbot.py
jasim_chatbot-0.1.0.dist-info/METADATA
jasim_chatbot-0.1.0.dist-info/WHEEL
jasim_chatbot-0.1.0.dist-info/entry_points.txt
jasim_chatbot-0.1.0.dist-info/top_level.txt
jasim_chatbot-0.1.0.dist-info/RECORD
